{
	"cmake" : 
	{
		"generator" : 
		{
			"multiConfig" : false,
			"name" : "MinGW Makefiles"
		},
		"paths" : 
		{
			"cmake" : "D:/CMake/bin/cmake.exe",
			"cpack" : "D:/CMake/bin/cpack.exe",
			"ctest" : "D:/CMake/bin/ctest.exe",
			"root" : "D:/CMake/share/cmake-3.31"
		},
		"version" : 
		{
			"isDirty" : false,
			"major" : 3,
			"minor" : 31,
			"patch" : 4,
			"string" : "3.31.4",
			"suffix" : ""
		}
	},
	"objects" : 
	[
		{
			"jsonFile" : "codemodel-v2-0655ca8a7ae004b2f392.json",
			"kind" : "codemodel",
			"version" : 
			{
				"major" : 2,
				"minor" : 7
			}
		},
		{
			"jsonFile" : "cache-v2-244b95b9114cc911d995.json",
			"kind" : "cache",
			"version" : 
			{
				"major" : 2,
				"minor" : 0
			}
		},
		{
			"jsonFile" : "cmakeFiles-v1-666b95d04ca9eb0073e4.json",
			"kind" : "cmakeFiles",
			"version" : 
			{
				"major" : 1,
				"minor" : 1
			}
		},
		{
			"jsonFile" : "toolchains-v1-b5356a046a6208ba34e8.json",
			"kind" : "toolchains",
			"version" : 
			{
				"major" : 1,
				"minor" : 0
			}
		}
	],
	"reply" : 
	{
		"cache-v2" : 
		{
			"jsonFile" : "cache-v2-244b95b9114cc911d995.json",
			"kind" : "cache",
			"version" : 
			{
				"major" : 2,
				"minor" : 0
			}
		},
		"cmakeFiles-v1" : 
		{
			"jsonFile" : "cmakeFiles-v1-666b95d04ca9eb0073e4.json",
			"kind" : "cmakeFiles",
			"version" : 
			{
				"major" : 1,
				"minor" : 1
			}
		},
		"codemodel-v2" : 
		{
			"jsonFile" : "codemodel-v2-0655ca8a7ae004b2f392.json",
			"kind" : "codemodel",
			"version" : 
			{
				"major" : 2,
				"minor" : 7
			}
		},
		"toolchains-v1" : 
		{
			"jsonFile" : "toolchains-v1-b5356a046a6208ba34e8.json",
			"kind" : "toolchains",
			"version" : 
			{
				"major" : 1,
				"minor" : 0
			}
		}
	}
}
